Metadata-Version: 2.1
Name: acapy_agent_jamie_testing
Version: 1.0.1
Summary: (ACA-Py) A Cloud Agent Python is a foundation for building decentralized identity applications and services running in non-mobile environments. 
Home-page: https://github.com/openwallet-foundation/acapy
License: Apache-2.0
Requires-Python: >=3.12,<4.0
Classifier: License :: OSI Approved :: Apache Software License
Classifier: Operating System :: OS Independent
Classifier: Programming Language :: Python :: 3
Classifier: Programming Language :: Python :: 3.12
Classifier: Programming Language :: Python :: 3.13
Provides-Extra: askar
Provides-Extra: bbs
Provides-Extra: didcommv2
Requires-Dist: ConfigArgParse (>=1.7,<1.8)
Requires-Dist: Markdown (>=3.7,<3.8)
Requires-Dist: aiohttp (>=3.10.5,<3.11.0)
Requires-Dist: aiohttp-apispec-acapy (>=3.0.2,<3.1.0)
Requires-Dist: aiohttp-cors (>=0.7.0,<0.8.0)
Requires-Dist: anoncreds (==0.2.0) ; extra == "askar"
Requires-Dist: apispec (>=6.6.0,<7.0.0)
Requires-Dist: aries-askar (>=0.3.2,<0.4.0) ; extra == "askar"
Requires-Dist: async-timeout (>=4.0.2,<4.1.0)
Requires-Dist: base58 (>=2.1.0,<2.2.0)
Requires-Dist: canonicaljson (>=2.0.0,<3.0.0)
Requires-Dist: deepmerge (>=0.3.0,<0.4.0)
Requires-Dist: did-peer-2 (>=0.1.2,<0.2.0)
Requires-Dist: did-peer-4 (>=0.1.4,<0.2.0)
Requires-Dist: didcomm-messaging (>=0.1.1a0,<0.2.0) ; extra == "didcommv2"
Requires-Dist: ecdsa (>=0.19.0,<0.20.0)
Requires-Dist: indy-credx (>=1.1.1,<1.2.0) ; extra == "askar"
Requires-Dist: indy-vdr (>=0.4.0,<0.5.0) ; extra == "askar"
Requires-Dist: jsonpath-ng (==1.6.1)
Requires-Dist: markupsafe (==2.1.5)
Requires-Dist: marshmallow (>=3.22.0,<3.23.0)
Requires-Dist: nest_asyncio (>=1.6.0,<1.7.0)
Requires-Dist: packaging (>=23.2,<23.3)
Requires-Dist: portalocker (>=2.10.1,<2.11.0)
Requires-Dist: prompt_toolkit (>=2.0.9,<2.1.0)
Requires-Dist: pydid (>=0.5.1,<0.6.0)
Requires-Dist: pyjwt (>=2.9.0,<2.10.0)
Requires-Dist: pyld (>=2.0.4,<3.0.0)
Requires-Dist: pynacl (>=1.5.0,<1.6.0)
Requires-Dist: python-dateutil (>=2.8.1,<2.9.0)
Requires-Dist: python-json-logger (>=2.0.7,<2.1.0)
Requires-Dist: pyyaml (>=6.0.2,<6.1.0)
Requires-Dist: qrcode[pil] (>=6.1,<7.0)
Requires-Dist: requests (>=2.32.3,<2.33.0)
Requires-Dist: rlp (==4.0.1)
Requires-Dist: sd-jwt (>=0.10.3,<0.11.0)
Requires-Dist: unflatten (>=0.2,<0.3)
Requires-Dist: ursa-bbs-signatures (>=1.0.1,<1.1.0) ; extra == "bbs"
Requires-Dist: uuid_utils (>=0.9.0,<0.10.0)
Project-URL: Repository, https://github.com/openwallet-foundation/acapy
